{"data": {"6ibELDe9PPNPzWvubcJ2WqDuQUndsvpkhQfQceeQpump": {"id": "6ibELDe9PPNPzWvubcJ2WqDuQUndsvpkhQfQceeQpump", "type": "buyPrice", "price": "0.0000039474", "extraInfo": {"lastSwappedPrice": {"lastJupiterSellAt": 1741848517, "lastJupiterSellPrice": "0.000005731972074782799", "lastJupiterBuyAt": null, "lastJupiterBuyPrice": null}, "quotedPrice": {"buyPrice": "0.0000039474", "buyAt": 1742077463, "sellPrice": null, "sellAt": null}, "confidenceLevel": "low", "depth": {"buyPriceImpactRatio": {"depth": {"10": 28.765053942263226, "100": null, "1000": null}, "timestamp": 1742077426}, "sellPriceImpactRatio": {"depth": {"10": null, "100": null, "1000": null}, "timestamp": null}}}}}, "timeTaken": 0.004023412}